opencitations_client/.DS_Store
opencitations_client/__init__.py
opencitations_client/__main__.py
opencitations_client/api.py
opencitations_client/cli.py
opencitations_client/download.py
opencitations_client/py.typed
opencitations_client/version.py
opencitations_client-0.0.6.dist-info/licenses/LICENSE
opencitations_client-0.0.6.dist-info/WHEEL
opencitations_client-0.0.6.dist-info/entry_points.txt
opencitations_client-0.0.6.dist-info/METADATA
opencitations_client-0.0.6.dist-info/RECORD
